{"CheckKeyTextTel":{},"CheckProfilTel":{},"CheckKeyTextPind":{},"CheckProfilPind":{},"id":2,"kodPacient":"PCN.0000000001","idCabinet":null,"age":78,"weight":89.00,"growth":170,"gender":"чол.","tel":"+380675540132","email":null,"name":"Микола","surname":"Павлюк","login":null,"password":null,"pind":"01234","profession":"шофер"}
{"CheckKeyTextTel":{},"CheckProfilTel":{},"CheckKeyTextPind":{},"CheckProfilPind":{},"id":1003,"kodPacient":"PCN.0000000003","idCabinet":null,"age":0,"weight":0.0,"growth":0,"gender":"чол.","tel":"","email":"","name":"Олександр","surname":"Павлов","login":null,"password":null,"pind":"","profession":""}
{"CheckKeyTextTel":{},"CheckProfilTel":{},"CheckKeyTextPind":{},"CheckProfilPind":{},"id":5004,"kodPacient":"PCN.0000000004","idCabinet":null,"age":0,"weight":0.0,"growth":0,"gender":"чол.","tel":"","email":"","name":"ывфыва","surname":"фывафывафыва","login":null,"password":null,"pind":"","profession":"ывафы"}
{"CheckKeyTextTel":{},"CheckProfilTel":{},"CheckKeyTextPind":{},"CheckProfilPind":{},"id":5005,"kodPacient":"PCN.0000000005","idCabinet":null,"age":0,"weight":0.0,"growth":0,"gender":"чол.","tel":"","email":"","name":"sdfsfa","surname":"asdfasdf","login":null,"password":null,"pind":"","profession":""}
{"CheckKeyTextTel":{},"CheckProfilTel":{},"CheckKeyTextPind":{},"CheckProfilPind":{},"id":5006,"kodPacient":"PCN.0000000006","idCabinet":null,"age":0,"weight":0.0,"growth":0,"gender":"чол.","tel":"","email":"","name":"asdfadf","surname":"asdfasdfas","login":null,"password":null,"pind":"","profession":""}
{"CheckKeyTextTel":{},"CheckProfilTel":{},"CheckKeyTextPind":{},"CheckProfilPind":{},"id":5007,"kodPacient":"PCN.0000000007","idCabinet":null,"age":0,"weight":0.0,"growth":0,"gender":"чол.","tel":"","email":"","name":"sdfasdfas","surname":"asdfasdfas","login":null,"password":null,"pind":"","profession":""}
{"CheckKeyTextTel":{},"CheckProfilTel":{},"CheckKeyTextPind":{},"CheckProfilPind":{},"id":5008,"kodPacient":"PCN.0000000008","idCabinet":null,"age":0,"weight":0.0,"growth":0,"gender":"чол.","tel":"","email":"","name":"asdfasdf","surname":"asdfasdfa","login":null,"password":null,"pind":"","profession":""}
{"CheckKeyTextTel":{},"CheckProfilTel":{},"CheckKeyTextPind":{},"CheckProfilPind":{},"id":5009,"kodPacient":"PCN.0000000009","idCabinet":null,"age":0,"weight":0.0,"growth":0,"gender":"чол.","tel":"","email":"","name":"asdasd","surname":"asdasdas","login":null,"password":null,"pind":"","profession":""}
{"CheckKeyTextTel":{},"CheckProfilTel":{},"CheckKeyTextPind":{},"CheckProfilPind":{},"id":5010,"kodPacient":"PCN.0000000010","idCabinet":null,"age":0,"weight":0.0,"growth":0,"gender":"чол.","tel":"","email":"","name":"asdasd","surname":"asdasda","login":null,"password":null,"pind":"","profession":""}
