{"CheckKeyTextTel":{},"CheckProfilTel":{},"CheckKeyTextPind":{},"CheckProfilPind":{},"id":1,"kodPacient":"PCN.0000000001","idCabinet":null,"age":78,"weight":89.00,"growth":170,"gender":"чол.","tel":"+380675540132","email":null,"name":"Микола","surname":"Павлюк","login":null,"password":null,"pind":"01234","profession":"шофер"}
{"CheckKeyTextTel":{},"CheckProfilTel":{},"CheckKeyTextPind":{},"CheckProfilPind":{},"id":4,"kodPacient":"PCN.0000000030","idCabinet":null,"age":0,"weight":0.0,"growth":0,"gender":"чол.","tel":"+380953514378","email":"","name":"Федір","surname":"Копитко","login":null,"password":null,"pind":"03146","profession":""}
{"CheckKeyTextTel":{},"CheckProfilTel":{},"CheckKeyTextPind":{},"CheckProfilPind":{},"id":7,"kodPacient":"PCN.0000000033","idCabinet":null,"age":69,"weight":0.0,"growth":0,"gender":"чол.","tel":"+380673452178","email":"","name":"Петро","surname":"Прокопенко","login":null,"password":null,"pind":"03127","profession":"водій"}
{"CheckKeyTextTel":{},"CheckProfilTel":{},"CheckKeyTextPind":{},"CheckProfilPind":{},"id":8,"kodPacient":"PCN.0000000034","idCabinet":null,"age":67,"weight":89.00,"growth":171,"gender":"чол.","tel":"+380964563245","email":"","name":"Петро","surname":"Козаков","login":null,"password":null,"pind":"03121","profession":"водій"}
{"CheckKeyTextTel":{},"CheckProfilTel":{},"CheckKeyTextPind":{},"CheckProfilPind":{},"id":9,"kodPacient":"PCN.0000000035","idCabinet":null,"age":73,"weight":84.00,"growth":181,"gender":"чол.","tel":"+380678215603","email":"","name":"Іван","surname":"Щірий","login":null,"password":null,"pind":"03521","profession":"механік"}
{"CheckKeyTextTel":{},"CheckProfilTel":{},"CheckKeyTextPind":{},"CheckProfilPind":{},"id":10,"kodPacient":"PCN.0000000036","idCabinet":null,"age":0,"weight":0.0,"growth":0,"gender":"чол.","tel":"+380505186449","email":"","name":"Ірина","surname":"Сидорова","login":null,"password":null,"pind":"","profession":""}
{"CheckKeyTextTel":{},"CheckProfilTel":{},"CheckKeyTextPind":{},"CheckProfilPind":{},"id":1002,"kodPacient":"PCN.0000000037","idCabinet":null,"age":67,"weight":0.0,"growth":167,"gender":"чол.","tel":"380295455632","email":"","name":"Павло","surname":"Курений","login":null,"password":null,"pind":"","profession":""}
{"CheckKeyTextTel":{},"CheckProfilTel":{},"CheckKeyTextPind":{},"CheckProfilPind":{},"id":2002,"kodPacient":"PCN.0000000038","idCabinet":null,"age":0,"weight":0.0,"growth":0,"gender":"чол.","tel":"0954567321","email":"","name":"МИкола","surname":"івафівпа","login":null,"password":null,"pind":"","profession":""}
